MANIFEST.in
README.rst
setup.cfg
setup.py
test.py
Ghost.py.egg-info/PKG-INFO
Ghost.py.egg-info/SOURCES.txt
Ghost.py.egg-info/dependency_links.txt
Ghost.py.egg-info/not-zip-safe
Ghost.py.egg-info/top_level.txt
docs/conf.py
docs/index.rst
docs/build/doctrees/environment.pickle
docs/build/doctrees/index.doctree
docs/build/html/.buildinfo
docs/build/html/genindex.html
docs/build/html/index.html
docs/build/html/objects.inv
docs/build/html/py-modindex.html
docs/build/html/search.html
docs/build/html/searchindex.js
docs/build/html/_sources/index.txt
docs/build/html/_static/ajax-loader.gif
docs/build/html/_static/basic.css
docs/build/html/_static/comment-bright.png
docs/build/html/_static/comment-close.png
docs/build/html/_static/comment.png
docs/build/html/_static/default.css
docs/build/html/_static/doctools.js
docs/build/html/_static/down-pressed.png
docs/build/html/_static/down.png
docs/build/html/_static/file.png
docs/build/html/_static/jquery.js
docs/build/html/_static/minus.png
docs/build/html/_static/plus.png
docs/build/html/_static/pygments.css
docs/build/html/_static/searchtools.js
docs/build/html/_static/sidebar.js
docs/build/html/_static/underscore.js
docs/build/html/_static/up-pressed.png
docs/build/html/_static/up.png
docs/build/html/_static/websupport.js
ghost/__init__.py
ghost/bindings.py
ghost/ghost.py
ghost/logger.py
ghost/test.py
ghost/ext/__init__.py
ghost/ext/django/__init__.py
ghost/ext/django/test.py
tests/__init__.py
tests/app.py
tests/run.py
tests/ghost/__init__.py
tests/ghost/bindings.py
tests/ghost/ghost.py
tests/ghost/logger.py
tests/ghost/test.py
tests/ghost/ext/__init__.py
tests/ghost/ext/django/__init__.py
tests/ghost/ext/django/test.py