Metadata-Version: 1.1
Name: Ghost.py
Version: 0.2.1
Summary: Webkit based webclient.
Home-page: https://github.com/jeanphix/Ghost.py
Author: Jean-Philippe Serafin
Author-email: serafinjp@gmail.com
License: mit
Platform: any
Classifier: Development Status :: 5 - Production/Stable
Classifier: Environment :: Web Environment
Classifier: Intended Audience :: Developers
Classifier: License :: OSI Approved :: MIT License
Classifier: Operating System :: OS Independent
Classifier: Programming Language :: Python
Classifier: Topic :: Internet :: WWW/HTTP :: Dynamic Content
Classifier: Topic :: Software Development :: Libraries :: Python Modules
